cleaned/__init__.py
cleaned/base.py
cleaned/errors.py
cleaned/fields.py
cleaned/py.typed
cleaned/utils.py
cleaned/version.py
cleand-1.3.1.dist-info/LICENSE
cleand-1.3.1.dist-info/METADATA
cleand-1.3.1.dist-info/WHEEL
cleand-1.3.1.dist-info/top_level.txt
cleand-1.3.1.dist-info/RECORD
