Metadata-Version: 2.1
Name: cleand
Version: 1.3.1
Summary: a declarative data validator
Home-page: https://github.com/saryou/cleaned
Author: Ryosuke Sasaki
Author-email: saryou.ssk@gmail.com
Project-URL: Bug Tracker, https://github.com/saryou/cleaned/issues
Classifier: Programming Language :: Python :: 3
Classifier: License :: OSI Approved :: MIT License
Classifier: Operating System :: OS Independent
Requires-Python: >=3.8
License-File: LICENSE
